rnaviewparser/__init__.py
rnaviewparser/parsetab.py
rnaviewparser/rnaview_ast.py
rnaviewparser/rnaview_data.py
rnaviewparser/rnaview_lex.py
rnaviewparser/rnaview_yacc.py
rnaviewparser/rnaviewparser.py
rnaviewparser-0.1.3.dist-info/METADATA
rnaviewparser-0.1.3.dist-info/RECORD
rnaviewparser-0.1.3.dist-info/WHEEL
rnaviewparser-0.1.3.dist-info/top_level.txt
