Metadata-Version: 2.1
Name: rnaviewparser
Version: 0.1.3
Summary: A RNAVIEW parser
Home-page: https://gitlab.climent-pommeret.red/Chopopope/rnaviewparser/
Author: Maria Climent-Pommeret
Author-email: maria@climent-pommeret.red
License: UNKNOWN
Keywords: RNA RNAVIEW parser
Platform: UNKNOWN
Classifier: Development Status :: 4 - Beta
Classifier: Intended Audience :: Science/Research
Classifier: Programming Language :: Python :: 3.7
Classifier: License :: OSI Approved :: MIT License
Classifier: Operating System :: OS Independent
Requires-Python: >=3.7
Requires-Dist: ply
Requires-Dist: pTable
